{
  "items": [
    {
      "name": "Nuxt",
      "link": "https://nuxt.com/",
      "icon": "custom:nuxt"
    },
    {
      "name": "Vue",
      "link": "https://vuejs.org/",
      "icon": "custom:vue"
    },
    {
      "name": "TailwindCSS",
      "link": "https://tailwindcss.com/",
      "icon": "custom:tailwind"
    },
    {
      "name": "TypeScript",
      "link": "https://www.typescriptlang.org/",
      "icon": "custom:typescript"
    },
        {
      "name": "Pinia",
      "link": "https://pinia.vuejs.org/",
      "icon": "custom:pinia"
    },
      {
      "name": "TanStack Vue Query",
      "link": "https://tanstack.com/query/latest/docs/vue/overview",
      "icon": "custom:query"
    },
        {
      "name": "i18n",
      "link": "https://vue-i18n.intlify.dev/",
      "icon": "custom:i18n"
    },
    {
      "name": "Vercel",
      "link": "https://vercel.com/",
      "icon": "custom:vercel"
    },
  
    {
      "name": "Notion",
      "link": "https://www.notion.so/",
      "icon": "custom:notion"
    },
    {
      "name": "Figma",
      "link": "https://www.figma.com/",
      "icon": "custom:figma"
    }
  ]
}
